split_gzip_upload/__init__.py
split_gzip_upload/io.py
split_gzip_upload/s3.py
split_gzip_upload/tool.py
split_gzip_upload_tool-0.0.1.dist-info/LICENSE
split_gzip_upload_tool-0.0.1.dist-info/METADATA
split_gzip_upload_tool-0.0.1.dist-info/WHEEL
split_gzip_upload_tool-0.0.1.dist-info/entry_points.txt
split_gzip_upload_tool-0.0.1.dist-info/top_level.txt
split_gzip_upload_tool-0.0.1.dist-info/RECORD
