Metadata-Version: 2.1
Name: split-gzip-upload-tool
Version: 0.0.1
Summary: Tool to split stdin, gzip it and upload to s3
Home-page: https://github.com/andriis/split-gzip-upload-tool
Author: Andrii Stepaniuk
Author-email: andrii.stepaniuk@gmail.com
License: UNKNOWN
Platform: UNKNOWN
Classifier: Development Status :: 3 - Alpha
Classifier: Programming Language :: Python :: 3
Classifier: Programming Language :: Python :: 3.6
Classifier: Programming Language :: Python :: 3.7
Requires-Dist: boto3
Requires-Dist: botocore
